.clang-format
.gitmodules
.readthedocs.yaml
CMakeLists.txt
CONTRIBUTING.md
Dockerfile
LICENSE
MANIFEST.in
README.md
requirements.txt
setup.py
cmake/FindAVX.cmake
cmake/SCAMPMacros.cmake
pyscamp.egg-info/PKG-INFO
pyscamp.egg-info/SOURCES.txt
pyscamp.egg-info/dependency_links.txt
pyscamp.egg-info/not-zip-safe
pyscamp.egg-info/top_level.txt
src/main.cpp
src/benchmark/CMakeLists.txt
src/benchmark/common.cpp
src/benchmark/common.h
src/benchmark/cpu_benchmarks.cpp
src/benchmark/gpu_benchmarks.cpp
src/common/CMakeLists.txt
src/common/common.cpp
src/common/common.h
src/common/profile.cpp
src/common/profile.h
src/common/scamp_args.cpp
src/common/scamp_args.h
src/common/scamp_exception.h
src/common/scamp_interface.cpp
src/common/scamp_interface.h
src/common/scamp_utils.cpp
src/common/scamp_utils.h
src/core/CMakeLists.txt
src/core/SCAMP.cpp
src/core/SCAMP.h
src/core/cpu_stats.cpp
src/core/cpu_stats.h
src/core/defines.h
src/core/kernel_common.cpp
src/core/kernel_common.h
src/core/kernel_gpu_utils.cu
src/core/kernel_gpu_utils.h
src/core/kernels.cu
src/core/kernels.h
src/core/kernels_compute.h
src/core/kernels_smem.h
src/core/qt_helper.cpp
src/core/qt_helper.h
src/core/qt_kernels.cu
src/core/qt_kernels.h
src/core/tile.cpp
src/core/tile.h
src/core/cpu_kernel/CMakeLists.txt
src/core/cpu_kernel/cpu_kernels.cpp
src/core/cpu_kernel/cpu_kernels.h
src/core/cpu_kernel/kernel_dispatcher.cpp
src/core/cpu_kernel/kernel_dispatcher.h
src/core/cpu_kernel/avx/CMakeLists.txt
src/core/cpu_kernel/avx/dispatch_avx.cpp
src/core/cpu_kernel/avx/dispatch_avx.h
src/core/cpu_kernel/avx2/CMakeLists.txt
src/core/cpu_kernel/avx2/dispatch_avx2.cpp
src/core/cpu_kernel/avx2/dispatch_avx2.h
src/core/cpu_kernel/baseline/CMakeLists.txt
src/core/cpu_kernel/baseline/dispatch_baseline.cpp
src/core/cpu_kernel/baseline/dispatch_baseline.h
src/distributed/CMakeLists.txt
src/distributed/distributed_job.cpp
src/distributed/distributed_job.h
src/distributed/distributed_tile.cpp
src/distributed/distributed_tile.h
src/distributed/job_list.cpp
src/distributed/job_list.h
src/distributed/scamp.proto
src/distributed/scamp_client.cc
src/distributed/scamp_interface.cpp
