Metadata-Version: 2.1
Name: pyscamp
Version: 4.0.1
Summary: SCAlable Matrix Profile
Home-page: https://github.com/zpzim/SCAMP
Author: Zachary Zimmerman
Author-email: zpzimmerman@gmail.com
License-File: LICENSE
